AkashTech_STT/__init__.py
akashtech_stt-0.1.0.dist-info/METADATA
akashtech_stt-0.1.0.dist-info/WHEEL
akashtech_stt-0.1.0.dist-info/top_level.txt
akashtech_stt-0.1.0.dist-info/RECORD
