Metadata-Version: 2.1
Name: akashtech-stt
Version: 0.1.0
Summary: This is Speech To Text package Created by Akash Kumar
Author: Akash Kumar
Author-email: akashofficial7256@gmail.com
